src/__init__.py
src/main.py
vecflow/__init__.py
vecflow/chat.py
vecflow/pipeline_setup/__init__.py
vecflow-0.0.2.dist-info/METADATA
vecflow-0.0.2.dist-info/WHEEL
vecflow-0.0.2.dist-info/top_level.txt
vecflow-0.0.2.dist-info/RECORD
