Metadata-Version: 2.1
Name: vecflow
Version: 0.0.2
Summary: VecFlow
Author: VecFlow
Author-email: <vecflowai@gmail.com>
Keywords: python,llms,data
Classifier: Development Status :: 1 - Planning
Classifier: Intended Audience :: Developers
Classifier: Programming Language :: Python :: 3
Classifier: Operating System :: MacOS :: MacOS X
